fal_client_fake/__init__.py
fal_client_fake/fal_client/__init__.py
fal_client_fake-0.3.0.dist-info/METADATA
fal_client_fake-0.3.0.dist-info/WHEEL
fal_client_fake-0.3.0.dist-info/licenses/LICENSE
fal_client_fake-0.3.0.dist-info/RECORD
